bizdatim.py
bizdatim-0.2.0.dist-info/DESCRIPTION.rst
bizdatim-0.2.0.dist-info/METADATA
bizdatim-0.2.0.dist-info/RECORD
bizdatim-0.2.0.dist-info/WHEEL
bizdatim-0.2.0.dist-info/metadata.json
bizdatim-0.2.0.dist-info/top_level.txt
