Metadata-Version: 2.0
Name: bizdatim
Version: 0.2.0
Summary: Module for performing simple business day arithmetic; forked from python-bizdatetime
Home-page: https://github.com/Polyconseil/bizdatim
Author: Polyconseil Dev Team
Author-email: opensource+bizdatim@polyconseil.fr
License: MIT
Platform: UNKNOWN
Classifier: Development Status :: 5 - Production/Stable
Classifier: License :: OSI Approved :: MIT License
Classifier: Operating System :: OS Independent
Classifier: Programming Language :: Python
Classifier: Programming Language :: Python :: 2.7
Classifier: Programming Language :: Python :: 3
Classifier: Topic :: Office/Business :: Scheduling
Classifier: Topic :: Software Development :: Libraries :: Python Modules
